./.flake8
./.gitignore
./.pre-commit-config.yaml
./LICENSE
./PKG-INFO
./README.md
./main.py
./pyproject.toml
./shell.nix
./.github/workflows/build.yml
./.github/workflows/build_and_publish_pypi.yml
./.github/workflows/manual_build.yml
./AppImage/OSCR.appdata.xml
./AppImage/OSCR.desktop
./AppImage/entrypoint.sh
./AppImage/requirements.txt
./OSCRUI/__init__.py
./OSCRUI/app.py
./OSCRUI/callbacks.py
./OSCRUI/datafunctions.py
./OSCRUI/datamodels.py
./OSCRUI/dialogs.py
./OSCRUI/displayer.py
./OSCRUI/iofunctions.py
./OSCRUI/leagueconnector.py
./OSCRUI/style.py
./OSCRUI/subwindows.py
./OSCRUI/textedit.py
./OSCRUI/translation.py
./OSCRUI/widgetbuilder.py
./OSCRUI/widgets.py
./assets/Overpass-Bold.ttf
./assets/Overpass-Medium.ttf
./assets/Overpass-Regular.ttf
./assets/RobotoMono-Medium.ttf
./assets/RobotoMono-Regular.ttf
./assets/TFO_advanced.png
./assets/TFO_elite.png
./assets/TFO_normal.png
./assets/check.svg
./assets/chevron-down.svg
./assets/chevron-right.svg
./assets/clear-plot.svg
./assets/close.svg
./assets/collapse-bottom.svg
./assets/collapse-left.svg
./assets/collapse-right.svg
./assets/collapse-top.svg
./assets/copy.svg
./assets/dash.svg
./assets/edit.svg
./assets/error.svg
./assets/expand-bottom.svg
./assets/expand-left.svg
./assets/expand-right.svg
./assets/expand-top.svg
./assets/export.svg
./assets/info.svg
./assets/ladder.svg
./assets/live-parser.svg
./assets/oscr.desktop
./assets/oscr_icon_small.ico
./assets/oscr_icon_small.png
./assets/oscrbanner-slim-dark-label.png
./assets/parser-down.svg
./assets/resize.svg
./assets/section31badge.png
./assets/snowflake.svg
./assets/star_minus.svg
./assets/star_plus.svg
./assets/stobuildslogo.png
./assets/thick-chevron-down.svg
./assets/warning.svg
./locales/de/LC_MESSAGES/messages.mo
./locales/de/LC_MESSAGES/messages.po
./locales/en/LC_MESSAGES/messages.mo
./locales/en/LC_MESSAGES/messages.po
./locales/fr/LC_MESSAGES/messages.mo
./locales/fr/LC_MESSAGES/messages.po
./locales/zh/LC_MESSAGES/messages.mo
oscr_ui-2025.9.14.1.dist-info/METADATA
oscr_ui-2025.9.14.1.dist-info/WHEEL
oscr_ui-2025.9.14.1.dist-info/entry_points.txt
oscr_ui-2025.9.14.1.dist-info/licenses/LICENSE
oscr_ui-2025.9.14.1.dist-info/RECORD
