Metadata-Version: 2.4
Name: OSCR-UI
Version: 2025.9.14.1
Summary: Open Source Combatlog Reader
Project-URL: Homepage, https://github.com/STOCD/OSCR-UI
Project-URL: Repository, https://github.com/STOCD/OSCR-UI.git
Project-URL: Bug Tracker, https://github.com/STOCD/OSCR-UI/issues
License:                     GNU GENERAL PUBLIC LICENSE
License-File: LICENSE
Classifier: Development Status :: 4 - Beta
Classifier: Programming Language :: Python
Requires-Python: >=3.12
Requires-Dist: cx-freeze==8.4.1
Requires-Dist: numpy==2.3.4
Requires-Dist: oscr-django-client>=2025.7.19.0
Requires-Dist: pydantic>=2.12.3
Requires-Dist: pyqtgraph==0.13.7
Requires-Dist: pyside6==6.10.0
Requires-Dist: sto-oscr>=2025.8.10.0
Provides-Extra: cli
Provides-Extra: gui
